{
  "CF101503364": {
    "contest_id": 1461,
    "language": "GNU C++17",
    "path": "codeforces\\1461\\D.cpp",
    "problem_index": "D",
    "problem_name": "Divide and Summarize",
    "problem_url": "https://codeforces.com/contest/1461/problem/D",
    "submission_id": "CF101503364",
    "submission_url": "https://codeforces.com/contest/1461/submission/101503364",
    "tags": [
      "binary search",
      "brute force",
      "data structures",
      "divide and conquer",
      "implementation",
      "sortings",
      "*1600"
    ],
    "timestamp": "Dec/17/2020 18:13"
  }
}